Metadata-Version: 2.1
Name: odoo12-addon-stock-change-price-at-date
Version: 12.0.1.0.0.99.dev8
Summary: This module allows to fill in a date in the standard wizard that changes product price. That helps accountant to add some product past values
Home-page: https://github.com/OCA/stock-logistics-workflow
Author: ACSONE SA/NV,Odoo Community Association (OCA)
Author-email: support@odoo-community.org
License: AGPL-3
Platform: UNKNOWN
Classifier: Programming Language :: Python
Classifier: Framework :: Odoo
Classifier: Framework :: Odoo :: 12.0
Classifier: License :: OSI Approved :: GNU Affero General Public License v3
Requires-Python: >=3.5
Requires-Dist: odoo <12.1dev,>=12.0a
